pymocko/__init__.py
pymocko/char.py
pymocko/date.py
pymocko/model.py
pymocko/num.py
pymocko/price.py
pymocko/word.py
pymocko-0.1.4.dist-info/LICENSE
pymocko-0.1.4.dist-info/METADATA
pymocko-0.1.4.dist-info/WHEEL
pymocko-0.1.4.dist-info/top_level.txt
pymocko-0.1.4.dist-info/RECORD
