Metadata-Version: 2.1
Name: pymocko
Version: 0.1.4
Summary: A package to generate mock data
Home-page: https://github.com/datnguye/pymocko
Author: datnguye
Author-email: datnguyen.it09@gmail.com
License: MIT
Platform: UNKNOWN
Requires-Python: >=3.7.5
